plcache/__init__.py
plcache/_args.py
plcache/_debugging.py
plcache/_dummy.py
plcache/_parse_sizes.py
plcache/config_dataclasses.py
plcache/decorator.py
plcache/paths.py
plcache/py.typed
plcache/symlinks.py
plcache/types.py
polars_diskcache-0.1.4.dist-info/METADATA
polars_diskcache-0.1.4.dist-info/WHEEL
polars_diskcache-0.1.4.dist-info/entry_points.txt
polars_diskcache-0.1.4.dist-info/licenses/LICENSE
polars_diskcache-0.1.4.dist-info/RECORD
