Metadata-Version: 2.1
Name: polars-diskcache
Version: 0.1.4
Summary: A diskcache decorator for Polars DataFrames and LazyFrames that saves function results as Parquet files
Author-Email: Louis Maddox <louismmx@gmail.com>
Requires-Python: >=3.13
Requires-Dist: diskcache>=5.6.3
Requires-Dist: ty-extensions>=0.1.0
Requires-Dist: xxhash>=3.5.0
